PyQTST/APIshermo.py
PyQTST/Moldata.py
PyQTST/Reaction.py
PyQTST/__init__.py
PyQTST-2.0.7.dist-info/LICENCE
PyQTST-2.0.7.dist-info/METADATA
PyQTST-2.0.7.dist-info/WHEEL
PyQTST-2.0.7.dist-info/entry_points.txt
PyQTST-2.0.7.dist-info/top_level.txt
PyQTST-2.0.7.dist-info/RECORD
